py_crunchbase/__init__.py
py_crunchbase/constants.py
py_crunchbase/decorators.py
py_crunchbase/main.py
py_crunchbase/paginator.py
py_crunchbase/query_builder.py
py_crunchbase/utils.py
py_crunchbase/apis/__init__.py
py_crunchbase/apis/base.py
py_crunchbase/apis/autocomplete/__init__.py
py_crunchbase/apis/autocomplete/api.py
py_crunchbase/apis/deleted_entities/__init__.py
py_crunchbase/apis/deleted_entities/api.py
py_crunchbase/apis/entities/__init__.py
py_crunchbase/apis/entities/base_.py
py_crunchbase/apis/entities/cards.py
py_crunchbase/apis/entities/entities_.py
py_crunchbase/apis/entities/main.py
py_crunchbase/apis/search/__init__.py
py_crunchbase/apis/search/api.py
py_crunchbase/apis/search/predicates.py
py_crunchbase/apis/search/query_builder.py
py_crunchbase/entities/__init__.py
py_crunchbase/entities/acquisitions.py
py_crunchbase/entities/addresses.py
py_crunchbase/entities/base.py
py_crunchbase/entities/categories.py
py_crunchbase/entities/category_groups.py
py_crunchbase/entities/degrees.py
py_crunchbase/entities/event_appearances.py
py_crunchbase/entities/events.py
py_crunchbase/entities/funding_rounds.py
py_crunchbase/entities/funds.py
py_crunchbase/entities/investments.py
py_crunchbase/entities/ipos.py
py_crunchbase/entities/jobs.py
py_crunchbase/entities/key_employee_changes.py
py_crunchbase/entities/layoffs.py
py_crunchbase/entities/locations.py
py_crunchbase/entities/organizations.py
py_crunchbase/entities/ownerships.py
py_crunchbase/entities/people.py
py_crunchbase/entities/press_references.py
py_crunchbase/entities/principals.py
py_crunchbase_api-0.1.1.dist-info/LICENSE
py_crunchbase_api-0.1.1.dist-info/METADATA
py_crunchbase_api-0.1.1.dist-info/WHEEL
py_crunchbase_api-0.1.1.dist-info/top_level.txt
py_crunchbase_api-0.1.1.dist-info/RECORD
