Metadata-Version: 2.1
Name: py-crunchbase-api
Version: 0.1.1
Summary: A python client for Crunchbase's REST API
Home-page: https://github.com/FahadNoor/py_crunchbase
Author: Fahad Noor
Author-email: fahad.noor91@gmail.com
License: MIT
Project-URL: Bug Tracker, https://github.com/FahadNoor/py_crunchbase/issues
Project-URL: Code, https://github.com/FahadNoor/py_crunchbase
Keywords: crunchbase,python crunchbase
Classifier: License :: OSI Approved :: MIT License
Classifier: Operating System :: OS Independent
Classifier: Intended Audience :: Developers
Classifier: Programming Language :: Python
Classifier: Programming Language :: Python :: 3
Classifier: Programming Language :: Python :: 3 :: Only
Classifier: Programming Language :: Python :: 3.6
Classifier: Programming Language :: Python :: 3.7
Classifier: Programming Language :: Python :: 3.8
Classifier: Programming Language :: Python :: 3.9
Classifier: Programming Language :: Python :: 3.10
Classifier: Programming Language :: Python :: 3.11
Requires-Python: >=3.6
License-File: LICENSE
Requires-Dist: requests (>=2.27.1)
